{"EQUATORIAL GUINEA": {"total_results": "286,000", "positive": {"recognizes": 19700, "allows": 34100, "issues": 35900, "classifies": 6620}, "negative": {"does not allow": 34700, "has forbidden": 31600, "restricts": 38100, "bans": 33900}, "score_ratio": -0.3035430224150398, "norm": 0.8203496503496504, "ss_pow": -0.24901141230425397, "hq": "regulation of cryptocurrencies", "pragmatic_actions": "(cryptocurrencies OR blockchain regulation OR mining OR cryptocurrencies as property OR crypto assets OR stablecoins OR CBDCs OR tokens OR ICOs OR cryptocurrencies as security OR cryptocurrency trading OR Bitcoin OR blockchain OR Bitcoin as legal tender OR NFTs)", "max": 138300, "positive_total": 96320, "negative_total": 138300, "country_hits": 286000}}